{
  "skatingDistanceLast10": [
    {
      "gameCenterLink": "/gamecenter/van-vs-sea/2026/02/28/2025020946",
      "gameDate": "2026-02-28",
      "isHomeTeam": true,
      "toiAll": 17640,
      "distanceSkatedAll": {
        "imperial": 45.4015,
        "metric": 73.0664
      },
      "toiEven": 16030,
      "distanceSkatedEven": {
        "imperial": 42.1064,
        "metric": 67.7635
      },
      "toiPP": 650,
      "distanceSkatedPP": {
        "imperial": 1.3108,
        "metric": 2.1096
      },
      "toiPK": 960,
      "distanceSkatedPK": {
        "imperial": 1.9842,
        "metric": 3.1933
      },
      "homeTeam": {
        "commonName": {
          "default": "Kraken"
        },
        "placeNameWithPreposition": {
          "default": "Seattle",
          "fr": "de Seattle"
        },
        "teamLogo": {
          "light": "https://assets.nhle.com/logos/nhl/svg/SEA_light.svg",
          "dark": "https://assets.nhle.com/logos/nhl/svg/SEA_dark.svg"
        }
      },
      "awayTeam": {
        "commonName": {
          "default": "Canucks"
        },
        "placeNameWithPreposition": {
          "default": "Vancouver",
          "fr": "de Vancouver"
        },
        "teamLogo": {
          "light": "https://assets.nhle.com/logos/nhl/svg/VAN_light.svg",
          "dark": "https://assets.nhle.com/logos/nhl/svg/VAN_dark.svg"
        }
      }
    },
    {
      "gameCenterLink": "/gamecenter/sea-vs-stl/2026/02/26/2025020925",
      "gameDate": "2026-02-26",
      "isHomeTeam": false,
      "toiAll": 18079,
      "distanceSkatedAll": {
        "imperial": 47.202,
        "metric": 75.9641
      },
      "toiEven": 16232,
      "distanceSkatedEven": {
        "imperial": 43.8931,
        "metric": 70.6389
      },
      "toiPP": 1847,
      "distanceSkatedPP": {
        "imperial": 3.3089,
        "metric": 5.3252
      },
      "homeTeam": {
        "commonName": {
          "default": "Blues"
        },
        "placeNameWithPreposition": {
          "default": "St. Louis",
          "fr": "de St. Louis"
        },
        "teamLogo": {
          "light": "https://assets.nhle.com/logos/nhl/svg/STL_light.svg?season=20252026",
          "dark": "https://assets.nhle.com/logos/nhl/svg/STL_dark.svg?season=20252026"
        }
      },
      "awayTeam": {
        "commonName": {
          "default": "Kraken"
        },
        "placeNameWithPreposition": {
          "default": "Seattle",
          "fr": "de Seattle"
        },
        "teamLogo": {
          "light": "https://assets.nhle.com/logos/nhl/svg/SEA_light.svg",
          "dark": "https://assets.nhle.com/logos/nhl/svg/SEA_dark.svg"
        }
      }
    },
    {
      "gameCenterLink": "/gamecenter/sea-vs-dal/2026/02/25/2025020913",
      "gameDate": "2026-02-25",
      "isHomeTeam": false,
      "toiAll": 17721,
      "distanceSkatedAll": {
        "imperial": 45.482,
        "metric": 73.196
      },
      "toiEven": 14205,
      "distanceSkatedEven": {
        "imperial": 37.6891,
        "metric": 60.6546
      },
      "toiPP": 2400,
      "distanceSkatedPP": {
        "imperial": 5.6176,
        "metric": 9.0407
      },
      "toiPK": 1116,
      "distanceSkatedPK": {
        "imperial": 2.1752,
        "metric": 3.5007
      },
      "homeTeam": {
        "commonName": {
          "default": "Stars"
        },
        "placeNameWithPreposition": {
          "default": "Dallas",
          "fr": "de Dallas"
        },
        "teamLogo": {
          "light": "https://assets.nhle.com/logos/nhl/svg/DAL_light.svg",
          "dark": "https://assets.nhle.com/logos/nhl/svg/DAL_dark.svg"
        }
      },
      "awayTeam": {
        "commonName": {
          "default": "Kraken"
        },
        "placeNameWithPreposition": {
          "default": "Seattle",
          "fr": "de Seattle"
        },
        "teamLogo": {
          "light": "https://assets.nhle.com/logos/nhl/svg/SEA_light.svg",
          "dark": "https://assets.nhle.com/logos/nhl/svg/SEA_dark.svg"
        }
      }
    },
    {
      "gameCenterLink": "/gamecenter/sea-vs-lak/2026/02/04/2025020902",
      "gameDate": "2026-02-04",
      "isHomeTeam": false,
      "toiAll": 17445,
      "distanceSkatedAll": {
        "imperial": 44.0503,
        "metric": 70.8919
      },
      "toiEven": 13025,
      "distanceSkatedEven": {
        "imperial": 33.6171,
        "metric": 54.1013
      },
      "toiPP": 3160,
      "distanceSkatedPP": {
        "imperial": 8.095,
        "metric": 13.0276
      },
      "toiPK": 1260,
      "distanceSkatedPK": {
        "imperial": 2.3382,
        "metric": 3.7629
      },
      "homeTeam": {
        "commonName": {
          "default": "Kings"
        },
        "placeNameWithPreposition": {
          "default": "Los Angeles",
          "fr": "de Los Angeles"
        },
        "teamLogo": {
          "light": "https://assets.nhle.com/logos/nhl/svg/LAK_light.svg",
          "dark": "https://assets.nhle.com/logos/nhl/svg/LAK_dark.svg"
        }
      },
      "awayTeam": {
        "commonName": {
          "default": "Kraken"
        },
        "placeNameWithPreposition": {
          "default": "Seattle",
          "fr": "de Seattle"
        },
        "teamLogo": {
          "light": "https://assets.nhle.com/logos/nhl/svg/SEA_light.svg",
          "dark": "https://assets.nhle.com/logos/nhl/svg/SEA_dark.svg"
        }
      }
    },
    {
      "gameCenterLink": "/gamecenter/sea-vs-ana/2026/02/03/2025020892",
      "gameDate": "2026-02-03",
      "isHomeTeam": false,
      "toiAll": 17748,
      "distanceSkatedAll": {
        "imperial": 44.3437,
        "metric": 71.364
      },
      "toiEven": 16353,
      "distanceSkatedEven": {
        "imperial": 41.575,
        "metric": 66.9083
      },
      "toiPK": 1395,
      "distanceSkatedPK": {
        "imperial": 2.7687,
        "metric": 4.4557
      },
      "homeTeam": {
        "commonName": {
          "default": "Ducks"
        },
        "placeNameWithPreposition": {
          "default": "Anaheim",
          "fr": "d'Anaheim"
        },
        "teamLogo": {
          "light": "https://assets.nhle.com/logos/nhl/svg/ANA_light.svg",
          "dark": "https://assets.nhle.com/logos/nhl/svg/ANA_dark.svg"
        }
      },
      "awayTeam": {
        "commonName": {
          "default": "Kraken"
        },
        "placeNameWithPreposition": {
          "default": "Seattle",
          "fr": "de Seattle"
        },
        "teamLogo": {
          "light": "https://assets.nhle.com/logos/nhl/svg/SEA_light.svg",
          "dark": "https://assets.nhle.com/logos/nhl/svg/SEA_dark.svg"
        }
      }
    },
    {
      "gameCenterLink": "/gamecenter/sea-vs-vgk/2026/01/31/2025020872",
      "gameDate": "2026-01-31",
      "isHomeTeam": false,
      "toiAll": 17859,
      "distanceSkatedAll": {
        "imperial": 46.5238,
        "metric": 74.8726
      },
      "toiEven": 16330,
      "distanceSkatedEven": {
        "imperial": 43.2148,
        "metric": 69.5472
      },
      "toiPP": 965,
      "distanceSkatedPP": {
        "imperial": 2.2558,
        "metric": 3.6303
      },
      "toiPK": 564,
      "distanceSkatedPK": {
        "imperial": 1.0532,
        "metric": 1.695
      },
      "homeTeam": {
        "commonName": {
          "default": "Golden Knights"
        },
        "placeNameWithPreposition": {
          "default": "Vegas",
          "fr": "de Vegas"
        },
        "teamLogo": {
          "light": "https://assets.nhle.com/logos/nhl/svg/VGK_light.svg",
          "dark": "https://assets.nhle.com/logos/nhl/svg/VGK_dark.svg"
        }
      },
      "awayTeam": {
        "commonName": {
          "default": "Kraken"
        },
        "placeNameWithPreposition": {
          "default": "Seattle",
          "fr": "de Seattle"
        },
        "teamLogo": {
          "light": "https://assets.nhle.com/logos/nhl/svg/SEA_light.svg",
          "dark": "https://assets.nhle.com/logos/nhl/svg/SEA_dark.svg"
        }
      }
    },
    {
      "gameCenterLink": "/gamecenter/tor-vs-sea/2026/01/29/2025020857",
      "gameDate": "2026-01-29",
      "isHomeTeam": true,
      "toiAll": 17693,
      "distanceSkatedAll": {
        "imperial": 45.7285,
        "metric": 73.5928
      },
      "toiEven": 15265,
      "distanceSkatedEven": {
        "imperial": 40.6204,
        "metric": 65.3721
      },
      "toiPP": 1200,
      "distanceSkatedPP": {
        "imperial": 2.804,
        "metric": 4.5126
      },
      "toiPK": 1228,
      "distanceSkatedPK": {
        "imperial": 2.3041,
        "metric": 3.7081
      },
      "homeTeam": {
        "commonName": {
          "default": "Kraken"
        },
        "placeNameWithPreposition": {
          "default": "Seattle",
          "fr": "de Seattle"
        },
        "teamLogo": {
          "light": "https://assets.nhle.com/logos/nhl/svg/SEA_light.svg",
          "dark": "https://assets.nhle.com/logos/nhl/svg/SEA_dark.svg"
        }
      },
      "awayTeam": {
        "commonName": {
          "default": "Maple Leafs"
        },
        "placeNameWithPreposition": {
          "default": "Toronto",
          "fr": "de Toronto"
        },
        "teamLogo": {
          "light": "https://assets.nhle.com/logos/nhl/svg/TOR_light.svg",
          "dark": "https://assets.nhle.com/logos/nhl/svg/TOR_dark.svg"
        }
      }
    },
    {
      "gameCenterLink": "/gamecenter/wsh-vs-sea/2026/01/27/2025020839",
      "gameDate": "2026-01-27",
      "isHomeTeam": true,
      "toiAll": 17457,
      "distanceSkatedAll": {
        "imperial": 44.054,
        "metric": 70.8979
      },
      "toiEven": 13274,
      "distanceSkatedEven": {
        "imperial": 35.5008,
        "metric": 57.1329
      },
      "toiPP": 2055,
      "distanceSkatedPP": {
        "imperial": 4.2997,
        "metric": 6.9196
      },
      "toiPK": 2128,
      "distanceSkatedPK": {
        "imperial": 4.2535,
        "metric": 6.8454
      },
      "homeTeam": {
        "commonName": {
          "default": "Kraken"
        },
        "placeNameWithPreposition": {
          "default": "Seattle",
          "fr": "de Seattle"
        },
        "teamLogo": {
          "light": "https://assets.nhle.com/logos/nhl/svg/SEA_light.svg",
          "dark": "https://assets.nhle.com/logos/nhl/svg/SEA_dark.svg"
        }
      },
      "awayTeam": {
        "commonName": {
          "default": "Capitals"
        },
        "placeNameWithPreposition": {
          "default": "Washington",
          "fr": "de Washington"
        },
        "teamLogo": {
          "light": "https://assets.nhle.com/logos/nhl/svg/WSH_secondary_light.svg",
          "dark": "https://assets.nhle.com/logos/nhl/svg/WSH_secondary_dark.svg"
        }
      }
    },
    {
      "gameCenterLink": "/gamecenter/njd-vs-sea/2026/01/25/2025020820",
      "gameDate": "2026-01-25",
      "isHomeTeam": true,
      "toiAll": 17654,
      "distanceSkatedAll": {
        "imperial": 44.755,
        "metric": 72.0261
      },
      "toiEven": 14707,
      "distanceSkatedEven": {
        "imperial": 38.5956,
        "metric": 62.1135
      },
      "toiPP": 1935,
      "distanceSkatedPP": {
        "imperial": 4.2988,
        "metric": 6.9182
      },
      "toiPK": 1012,
      "distanceSkatedPK": {
        "imperial": 1.8606,
        "metric": 2.9944
      },
      "homeTeam": {
        "commonName": {
          "default": "Kraken"
        },
        "placeNameWithPreposition": {
          "default": "Seattle",
          "fr": "de Seattle"
        },
        "teamLogo": {
          "light": "https://assets.nhle.com/logos/nhl/svg/SEA_light.svg",
          "dark": "https://assets.nhle.com/logos/nhl/svg/SEA_dark.svg"
        }
      },
      "awayTeam": {
        "commonName": {
          "default": "Devils"
        },
        "placeNameWithPreposition": {
          "default": "New Jersey",
          "fr": "du New Jersey"
        },
        "teamLogo": {
          "light": "https://assets.nhle.com/logos/nhl/svg/NJD_light.svg",
          "dark": "https://assets.nhle.com/logos/nhl/svg/NJD_dark.svg"
        }
      }
    },
    {
      "gameCenterLink": "/gamecenter/ana-vs-sea/2026/01/23/2025020809",
      "gameDate": "2026-01-23",
      "isHomeTeam": true,
      "toiAll": 17877,
      "distanceSkatedAll": {
        "imperial": 48.3717,
        "metric": 77.8465
      },
      "toiEven": 16139,
      "distanceSkatedEven": {
        "imperial": 44.2267,
        "metric": 71.1758
      },
      "toiPP": 1050,
      "distanceSkatedPP": {
        "imperial": 2.6382,
        "metric": 4.2458
      },
      "toiPK": 688,
      "distanceSkatedPK": {
        "imperial": 1.5068,
        "metric": 2.425
      },
      "homeTeam": {
        "commonName": {
          "default": "Kraken"
        },
        "placeNameWithPreposition": {
          "default": "Seattle",
          "fr": "de Seattle"
        },
        "teamLogo": {
          "light": "https://assets.nhle.com/logos/nhl/svg/SEA_light.svg",
          "dark": "https://assets.nhle.com/logos/nhl/svg/SEA_dark.svg"
        }
      },
      "awayTeam": {
        "commonName": {
          "default": "Ducks"
        },
        "placeNameWithPreposition": {
          "default": "Anaheim",
          "fr": "d'Anaheim"
        },
        "teamLogo": {
          "light": "https://assets.nhle.com/logos/nhl/svg/ANA_light.svg",
          "dark": "https://assets.nhle.com/logos/nhl/svg/ANA_dark.svg"
        }
      }
    }
  ],
  "skatingDistanceDetails": [
    {
      "strengthCode": "all",
      "positionCode": "all",
      "distanceTotal": {
        "imperial": 2724.3741,
        "metric": 4384.2411,
        "rank": 13,
        "leagueAvg": {
          "imperial": 2701.1864,
          "metric": 4346.9259
        }
      },
      "distancePer60": {
        "imperial": 9.2846,
        "metric": 14.9414,
        "rank": 6,
        "leagueAvg": {
          "imperial": 9.1633,
          "metric": 14.7462
        }
      },
      "distanceMaxGame": {
        "imperial": 49.0874,
        "metric": 78.9947,
        "rank": 15,
        "leagueAvg": {
          "imperial": 49.2112,
          "metric": 79.1939
        },
        "overlay": {
          "gameDate": "2025-12-29",
          "awayTeam": {
            "abbrev": "VAN",
            "score": 3
          },
          "homeTeam": {
            "abbrev": "SEA",
            "score": 2
          },
          "gameOutcome": {
            "lastPeriodType": "SO"
          },
          "periodDescriptor": {
            "maxRegulationPeriods": 3,
            "number": 1,
            "periodType": "REG"
          },
          "gameType": 2
        }
      },
      "distanceMaxPeriod": {
        "imperial": 16.8113,
        "metric": 27.0539,
        "rank": 5,
        "leagueAvg": {
          "imperial": 16.5675,
          "metric": 26.6615
        },
        "overlay": {
          "gameDate": "2026-01-27",
          "awayTeam": {
            "abbrev": "WSH",
            "score": 1
          },
          "homeTeam": {
            "abbrev": "SEA",
            "score": 5
          },
          "gameOutcome": {
            "lastPeriodType": "REG"
          },
          "periodDescriptor": {
            "maxRegulationPeriods": 3,
            "number": 1,
            "periodType": "REG"
          },
          "gameType": 2
        }
      }
    },
    {
      "strengthCode": "all",
      "positionCode": "F",
      "distanceTotal": {
        "imperial": 1755.2402,
        "metric": 2824.6475,
        "rank": 5,
        "leagueAvg": {
          "imperial": 1720.9243,
          "metric": 2769.4241
        }
      },
      "distancePer60": {
        "imperial": 9.8302,
        "metric": 15.8195,
        "rank": 1,
        "leagueAvg": {
          "imperial": 9.6019,
          "metric": 15.452
        }
      },
      "distanceMaxGame": {
        "imperial": 32.3341,
        "metric": 52.0341,
        "rank": 6,
        "leagueAvg": {
          "imperial": 31.5576,
          "metric": 50.7846
        },
        "overlay": {
          "gameDate": "2025-12-29",
          "awayTeam": {
            "abbrev": "VAN",
            "score": 3
          },
          "homeTeam": {
            "abbrev": "SEA",
            "score": 2
          },
          "gameOutcome": {
            "lastPeriodType": "SO"
          },
          "periodDescriptor": {
            "maxRegulationPeriods": 3,
            "number": 1,
            "periodType": "REG"
          },
          "gameType": 2
        }
      },
      "distanceMaxPeriod": {
        "imperial": 10.7442,
        "metric": 17.2902,
        "rank": 16,
        "leagueAvg": {
          "imperial": 10.7481,
          "metric": 17.2965
        },
        "overlay": {
          "gameDate": "2026-01-27",
          "awayTeam": {
            "abbrev": "WSH",
            "score": 1
          },
          "homeTeam": {
            "abbrev": "SEA",
            "score": 5
          },
          "gameOutcome": {
            "lastPeriodType": "REG"
          },
          "periodDescriptor": {
            "maxRegulationPeriods": 3,
            "number": 1,
            "periodType": "REG"
          },
          "gameType": 2
        }
      }
    },
    {
      "strengthCode": "all",
      "positionCode": "D",
      "distanceTotal": {
        "imperial": 969.1339,
        "metric": 1559.5937,
        "rank": 23,
        "leagueAvg": {
          "imperial": 980.262,
          "metric": 1577.5019
        }
      },
      "distancePer60": {
        "imperial": 8.4365,
        "metric": 13.5766,
        "rank": 23,
        "leagueAvg": {
          "imperial": 8.4831,
          "metric": 13.6515
        }
      },
      "distanceMaxGame": {
        "imperial": 17.768,
        "metric": 28.5934,
        "rank": 26,
        "leagueAvg": {
          "imperial": 18.1817,
          "metric": 29.2592
        },
        "overlay": {
          "gameDate": "2026-01-23",
          "awayTeam": {
            "abbrev": "ANA",
            "score": 4
          },
          "homeTeam": {
            "abbrev": "SEA",
            "score": 2
          },
          "gameOutcome": {
            "lastPeriodType": "REG"
          },
          "periodDescriptor": {
            "maxRegulationPeriods": 3,
            "number": 1,
            "periodType": "REG"
          },
          "gameType": 2
        }
      },
      "distanceMaxPeriod": {
        "imperial": 6.2679,
        "metric": 10.0868,
        "rank": 11,
        "leagueAvg": {
          "imperial": 6.224,
          "metric": 10.0161
        },
        "overlay": {
          "gameDate": "2025-10-11",
          "awayTeam": {
            "abbrev": "VGK",
            "score": 1
          },
          "homeTeam": {
            "abbrev": "SEA",
            "score": 2
          },
          "gameOutcome": {
            "lastPeriodType": "OT",
            "otPeriods": 1
          },
          "periodDescriptor": {
            "maxRegulationPeriods": 3,
            "number": 1,
            "periodType": "REG"
          },
          "gameType": 2
        }
      }
    },
    {
      "strengthCode": "pp",
      "positionCode": "all",
      "distanceTotal": {
        "imperial": 189.5782,
        "metric": 305.0816,
        "rank": 23,
        "leagueAvg": {
          "imperial": 200.1951,
          "metric": 322.167
        }
      },
      "distancePer60": {
        "imperial": 8.3687,
        "metric": 13.4674,
        "rank": 19,
        "leagueAvg": {
          "imperial": 8.3807,
          "metric": 13.4868
        }
      },
      "distanceMaxGame": {
        "imperial": 8.1594,
        "metric": 13.1307,
        "rank": 16,
        "leagueAvg": {
          "imperial": 8.1572,
          "metric": 13.1272
        },
        "overlay": {
          "gameDate": "2025-11-05",
          "awayTeam": {
            "abbrev": "SJS",
            "score": 6
          },
          "homeTeam": {
            "abbrev": "SEA",
            "score": 1
          },
          "gameOutcome": {
            "lastPeriodType": "REG"
          },
          "periodDescriptor": {
            "maxRegulationPeriods": 3,
            "number": 3,
            "periodType": "REG"
          },
          "gameType": 2
        }
      },
      "distanceMaxPeriod": {
        "imperial": 4.3045,
        "metric": 6.927,
        "rank": 28,
        "leagueAvg": {
          "imperial": 4.8248,
          "metric": 7.7644
        },
        "overlay": {
          "gameDate": "2025-11-05",
          "awayTeam": {
            "abbrev": "SJS",
            "score": 6
          },
          "homeTeam": {
            "abbrev": "SEA",
            "score": 1
          },
          "gameOutcome": {
            "lastPeriodType": "REG"
          },
          "periodDescriptor": {
            "maxRegulationPeriods": 3,
            "number": 3,
            "periodType": "REG"
          },
          "gameType": 2
        }
      }
    },
    {
      "strengthCode": "pp",
      "positionCode": "F",
      "distanceTotal": {
        "imperial": 147.8114,
        "metric": 237.8678,
        "rank": 22,
        "leagueAvg": {
          "imperial": 153.5228,
          "metric": 247.0589
        }
      },
      "distancePer60": {
        "imperial": 8.3034,
        "metric": 13.3623,
        "rank": 15,
        "leagueAvg": {
          "imperial": 8.2539,
          "metric": 13.2826
        }
      },
      "distanceMaxGame": {
        "imperial": 6.271,
        "metric": 10.0917,
        "rank": 14,
        "leagueAvg": {
          "imperial": 6.2995,
          "metric": 10.1376
        },
        "overlay": {
          "gameDate": "2025-11-05",
          "awayTeam": {
            "abbrev": "SJS",
            "score": 6
          },
          "homeTeam": {
            "abbrev": "SEA",
            "score": 1
          },
          "gameOutcome": {
            "lastPeriodType": "REG"
          },
          "periodDescriptor": {
            "maxRegulationPeriods": 3,
            "number": 3,
            "periodType": "REG"
          },
          "gameType": 2
        }
      },
      "distanceMaxPeriod": {
        "imperial": 3.2833,
        "metric": 5.2838,
        "rank": 27,
        "leagueAvg": {
          "imperial": 3.7113,
          "metric": 5.9726
        },
        "overlay": {
          "gameDate": "2026-02-04",
          "awayTeam": {
            "abbrev": "SEA",
            "score": 4
          },
          "homeTeam": {
            "abbrev": "LAK",
            "score": 2
          },
          "gameOutcome": {
            "lastPeriodType": "REG"
          },
          "periodDescriptor": {
            "maxRegulationPeriods": 3,
            "number": 3,
            "periodType": "REG"
          },
          "gameType": 2
        }
      }
    },
    {
      "strengthCode": "pp",
      "positionCode": "D",
      "distanceTotal": {
        "imperial": 41.7668,
        "metric": 67.2138,
        "rank": 27,
        "leagueAvg": {
          "imperial": 46.6723,
          "metric": 75.1081
        }
      },
      "distancePer60": {
        "imperial": 8.6083,
        "metric": 13.853,
        "rank": 28,
        "leagueAvg": {
          "imperial": 8.827,
          "metric": 14.2049
        }
      },
      "distanceMaxGame": {
        "imperial": 1.8884,
        "metric": 3.039,
        "rank": 18,
        "leagueAvg": {
          "imperial": 2.0082,
          "metric": 3.2318
        },
        "overlay": {
          "gameDate": "2025-11-05",
          "awayTeam": {
            "abbrev": "SJS",
            "score": 6
          },
          "homeTeam": {
            "abbrev": "SEA",
            "score": 1
          },
          "gameOutcome": {
            "lastPeriodType": "REG"
          },
          "periodDescriptor": {
            "maxRegulationPeriods": 3,
            "number": 3,
            "periodType": "REG"
          },
          "gameType": 2
        }
      },
      "distanceMaxPeriod": {
        "imperial": 1.0765,
        "metric": 1.7324,
        "rank": 19,
        "leagueAvg": {
          "imperial": 1.2204,
          "metric": 1.964
        },
        "overlay": {
          "gameDate": "2025-11-05",
          "awayTeam": {
            "abbrev": "SJS",
            "score": 6
          },
          "homeTeam": {
            "abbrev": "SEA",
            "score": 1
          },
          "gameOutcome": {
            "lastPeriodType": "REG"
          },
          "periodDescriptor": {
            "maxRegulationPeriods": 3,
            "number": 3,
            "periodType": "REG"
          },
          "gameType": 2
        }
      }
    },
    {
      "strengthCode": "pk",
      "positionCode": "all",
      "distanceTotal": {
        "imperial": 120.224,
        "metric": 193.4723,
        "rank": 31,
        "leagueAvg": {
          "imperial": 144.3847,
          "metric": 232.3533
        }
      },
      "distancePer60": {
        "imperial": 7.2203,
        "metric": 11.6194,
        "rank": 30,
        "leagueAvg": {
          "imperial": 7.6061,
          "metric": 12.2402
        }
      },
      "distanceMaxGame": {
        "imperial": 5.214,
        "metric": 8.3907,
        "rank": 23,
        "leagueAvg": {
          "imperial": 5.9523,
          "metric": 9.5787
        },
        "overlay": {
          "gameDate": "2026-01-21",
          "awayTeam": {
            "abbrev": "NYI",
            "score": 1
          },
          "homeTeam": {
            "abbrev": "SEA",
            "score": 4
          },
          "gameOutcome": {
            "lastPeriodType": "REG"
          },
          "periodDescriptor": {
            "maxRegulationPeriods": 3,
            "number": 3,
            "periodType": "REG"
          },
          "gameType": 2
        }
      },
      "distanceMaxPeriod": {
        "imperial": 3.3387,
        "metric": 5.3729,
        "rank": 16,
        "leagueAvg": {
          "imperial": 3.4461,
          "metric": 5.5457
        },
        "overlay": {
          "gameDate": "2026-01-27",
          "awayTeam": {
            "abbrev": "WSH",
            "score": 1
          },
          "homeTeam": {
            "abbrev": "SEA",
            "score": 5
          },
          "gameOutcome": {
            "lastPeriodType": "REG"
          },
          "periodDescriptor": {
            "maxRegulationPeriods": 3,
            "number": 3,
            "periodType": "REG"
          },
          "gameType": 2
        }
      }
    },
    {
      "strengthCode": "pk",
      "positionCode": "F",
      "distanceTotal": {
        "imperial": 67.3151,
        "metric": 108.3278,
        "rank": 30,
        "leagueAvg": {
          "imperial": 79.4847,
          "metric": 127.912
        }
      },
      "distancePer60": {
        "imperial": 8.1372,
        "metric": 13.0949,
        "rank": 25,
        "leagueAvg": {
          "imperial": 8.4695,
          "metric": 13.6297
        }
      },
      "distanceMaxGame": {
        "imperial": 2.8807,
        "metric": 4.6358,
        "rank": 23,
        "leagueAvg": {
          "imperial": 3.2574,
          "metric": 5.242
        },
        "overlay": {
          "gameDate": "2026-01-21",
          "awayTeam": {
            "abbrev": "NYI",
            "score": 1
          },
          "homeTeam": {
            "abbrev": "SEA",
            "score": 4
          },
          "gameOutcome": {
            "lastPeriodType": "REG"
          },
          "periodDescriptor": {
            "maxRegulationPeriods": 3,
            "number": 3,
            "periodType": "REG"
          },
          "gameType": 2
        }
      },
      "distanceMaxPeriod": {
        "imperial": 1.8875,
        "metric": 3.0374,
        "rank": 15,
        "leagueAvg": {
          "imperial": 1.897,
          "metric": 3.0528
        },
        "overlay": {
          "gameDate": "2026-01-27",
          "awayTeam": {
            "abbrev": "WSH",
            "score": 1
          },
          "homeTeam": {
            "abbrev": "SEA",
            "score": 5
          },
          "gameOutcome": {
            "lastPeriodType": "REG"
          },
          "periodDescriptor": {
            "maxRegulationPeriods": 3,
            "number": 3,
            "periodType": "REG"
          },
          "gameType": 2
        }
      }
    },
    {
      "strengthCode": "pk",
      "positionCode": "D",
      "distanceTotal": {
        "imperial": 52.9089,
        "metric": 85.1445,
        "rank": 30,
        "leagueAvg": {
          "imperial": 64.9,
          "metric": 104.4413
        }
      },
      "distancePer60": {
        "imperial": 6.315,
        "metric": 10.1625,
        "rank": 30,
        "leagueAvg": {
          "imperial": 6.7618,
          "metric": 10.8816
        }
      },
      "distanceMaxGame": {
        "imperial": 2.3333,
        "metric": 3.7549,
        "rank": 25,
        "leagueAvg": {
          "imperial": 2.7144,
          "metric": 4.3682
        },
        "overlay": {
          "gameDate": "2026-01-21",
          "awayTeam": {
            "abbrev": "NYI",
            "score": 1
          },
          "homeTeam": {
            "abbrev": "SEA",
            "score": 4
          },
          "gameOutcome": {
            "lastPeriodType": "REG"
          },
          "periodDescriptor": {
            "maxRegulationPeriods": 3,
            "number": 3,
            "periodType": "REG"
          },
          "gameType": 2
        }
      },
      "distanceMaxPeriod": {
        "imperial": 1.4513,
        "metric": 2.3355,
        "rank": 19,
        "leagueAvg": {
          "imperial": 1.5696,
          "metric": 2.5259
        },
        "overlay": {
          "gameDate": "2026-01-27",
          "awayTeam": {
            "abbrev": "WSH",
            "score": 1
          },
          "homeTeam": {
            "abbrev": "SEA",
            "score": 5
          },
          "gameOutcome": {
            "lastPeriodType": "REG"
          },
          "periodDescriptor": {
            "maxRegulationPeriods": 3,
            "number": 3,
            "periodType": "REG"
          },
          "gameType": 2
        }
      }
    },
    {
      "strengthCode": "es",
      "positionCode": "all",
      "distanceTotal": {
        "imperial": 2414.5719,
        "metric": 3885.6872,
        "rank": 8,
        "leagueAvg": {
          "imperial": 2356.6066,
          "metric": 3792.4056
        }
      },
      "distancePer60": {
        "imperial": 9.5015,
        "metric": 15.2905,
        "rank": 6,
        "leagueAvg": {
          "imperial": 9.3549,
          "metric": 15.0545
        }
      },
      "distanceMaxGame": {
        "imperial": 45.9114,
        "metric": 73.8837,
        "rank": 26,
        "leagueAvg": {
          "imperial": 46.6903,
          "metric": 75.1371
        },
        "overlay": {
          "gameDate": "2025-11-23",
          "awayTeam": {
            "abbrev": "SEA",
            "score": 0
          },
          "homeTeam": {
            "abbrev": "NYI",
            "score": 1
          },
          "gameOutcome": {
            "lastPeriodType": "SO"
          },
          "periodDescriptor": {
            "maxRegulationPeriods": 3,
            "number": 1,
            "periodType": "REG"
          },
          "gameType": 2
        }
      },
      "distanceMaxPeriod": {
        "imperial": 16.8039,
        "metric": 27.0419,
        "rank": 4,
        "leagueAvg": {
          "imperial": 16.4705,
          "metric": 26.5054
        },
        "overlay": {
          "gameDate": "2025-10-11",
          "awayTeam": {
            "abbrev": "VGK",
            "score": 1
          },
          "homeTeam": {
            "abbrev": "SEA",
            "score": 2
          },
          "gameOutcome": {
            "lastPeriodType": "OT",
            "otPeriods": 1
          },
          "periodDescriptor": {
            "maxRegulationPeriods": 3,
            "number": 1,
            "periodType": "REG"
          },
          "gameType": 2
        }
      }
    },
    {
      "strengthCode": "es",
      "positionCode": "F",
      "distanceTotal": {
        "imperial": 1540.1138,
        "metric": 2478.4519,
        "rank": 4,
        "leagueAvg": {
          "imperial": 1487.9168,
          "metric": 2394.4532
        }
      },
      "distancePer60": {
        "imperial": 10.1004,
        "metric": 16.2542,
        "rank": 2,
        "leagueAvg": {
          "imperial": 9.8379,
          "metric": 15.8318
        }
      },
      "distanceMaxGame": {
        "imperial": 29.5017,
        "metric": 47.4761,
        "rank": 21,
        "leagueAvg": {
          "imperial": 29.5264,
          "metric": 47.5158
        },
        "overlay": {
          "gameDate": "2025-11-23",
          "awayTeam": {
            "abbrev": "SEA",
            "score": 0
          },
          "homeTeam": {
            "abbrev": "NYI",
            "score": 1
          },
          "gameOutcome": {
            "lastPeriodType": "SO"
          },
          "periodDescriptor": {
            "maxRegulationPeriods": 3,
            "number": 1,
            "periodType": "REG"
          },
          "gameType": 2
        }
      },
      "distanceMaxPeriod": {
        "imperial": 10.5806,
        "metric": 17.027,
        "rank": 8,
        "leagueAvg": {
          "imperial": 10.4549,
          "metric": 16.8246
        },
        "overlay": {
          "gameDate": "2025-11-11",
          "awayTeam": {
            "abbrev": "CBJ",
            "score": 2
          },
          "homeTeam": {
            "abbrev": "SEA",
            "score": 1
          },
          "gameOutcome": {
            "lastPeriodType": "SO"
          },
          "periodDescriptor": {
            "maxRegulationPeriods": 3,
            "number": 1,
            "periodType": "REG"
          },
          "gameType": 2
        }
      }
    },
    {
      "strengthCode": "es",
      "positionCode": "D",
      "distanceTotal": {
        "imperial": 874.4581,
        "metric": 1407.2353,
        "rank": 14,
        "leagueAvg": {
          "imperial": 868.6898,
          "metric": 1397.9524
        }
      },
      "distancePer60": {
        "imperial": 8.6032,
        "metric": 13.8448,
        "rank": 22,
        "leagueAvg": {
          "imperial": 8.6291,
          "metric": 13.8866
        }
      },
      "distanceMaxGame": {
        "imperial": 16.5122,
        "metric": 26.5725,
        "rank": 29,
        "leagueAvg": {
          "imperial": 17.2617,
          "metric": 27.7786
        },
        "overlay": {
          "gameDate": "2026-01-23",
          "awayTeam": {
            "abbrev": "ANA",
            "score": 4
          },
          "homeTeam": {
            "abbrev": "SEA",
            "score": 2
          },
          "gameOutcome": {
            "lastPeriodType": "REG"
          },
          "periodDescriptor": {
            "maxRegulationPeriods": 3,
            "number": 1,
            "periodType": "REG"
          },
          "gameType": 2
        }
      },
      "distanceMaxPeriod": {
        "imperial": 6.2679,
        "metric": 10.0868,
        "rank": 7,
        "leagueAvg": {
          "imperial": 6.1716,
          "metric": 9.9318
        },
        "overlay": {
          "gameDate": "2025-10-11",
          "awayTeam": {
            "abbrev": "VGK",
            "score": 1
          },
          "homeTeam": {
            "abbrev": "SEA",
            "score": 2
          },
          "gameOutcome": {
            "lastPeriodType": "OT",
            "otPeriods": 1
          },
          "periodDescriptor": {
            "maxRegulationPeriods": 3,
            "number": 1,
            "periodType": "REG"
          },
          "gameType": 2
        }
      }
    }
  ]
}